odoo/addons/account_move_reconcile_forbid_cancel/README.rst
odoo/addons/account_move_reconcile_forbid_cancel/__init__.py
odoo/addons/account_move_reconcile_forbid_cancel/__manifest__.py
odoo/addons/account_move_reconcile_forbid_cancel/i18n/account_move_reconcile_forbid_cancel.pot
odoo/addons/account_move_reconcile_forbid_cancel/i18n/es.po
odoo/addons/account_move_reconcile_forbid_cancel/i18n/it.po
odoo/addons/account_move_reconcile_forbid_cancel/i18n/pt_BR.po
odoo/addons/account_move_reconcile_forbid_cancel/i18n/sv.po
odoo/addons/account_move_reconcile_forbid_cancel/models/__init__.py
odoo/addons/account_move_reconcile_forbid_cancel/models/account_move.py
odoo/addons/account_move_reconcile_forbid_cancel/readme/CONTRIBUTORS.md
odoo/addons/account_move_reconcile_forbid_cancel/readme/DESCRIPTION.md
odoo/addons/account_move_reconcile_forbid_cancel/readme/USAGE.md
odoo/addons/account_move_reconcile_forbid_cancel/static/description/icon.png
odoo/addons/account_move_reconcile_forbid_cancel/static/description/index.html
odoo/addons/account_move_reconcile_forbid_cancel/tests/__init__.py
odoo/addons/account_move_reconcile_forbid_cancel/tests/test_account_move_reconcile_forbid_cancel.py
odoo_addon_account_move_reconcile_forbid_cancel-18.0.1.0.0.2.dist-info/METADATA
odoo_addon_account_move_reconcile_forbid_cancel-18.0.1.0.0.2.dist-info/WHEEL
odoo_addon_account_move_reconcile_forbid_cancel-18.0.1.0.0.2.dist-info/top_level.txt
odoo_addon_account_move_reconcile_forbid_cancel-18.0.1.0.0.2.dist-info/RECORD
